bpa/__init__.py
bpa/bill_classify.py
bpa/bill_similarity_search.py
bpa/classifier.py
bpa/global_variables.py
bpa/searcher.py
bpa/tokenizer.py
bpa/util.py
bpa/db/standard-bills.txt
bpa/dicts/stopwords.txt
bpa/dicts/userdict.txt
bpa/t1_model/label_2_type.dict
bpa/t1_model/model.joblib
bpa/t1_model/type_2_label.dict
bpa/t1_model/vectorizer.joblib
bpa/t2_model/database_vectors.joblib
bpa/t2_model/ordinal_2_id.dict
bpa/t2_model/vectorizer.joblib
tests/__init__.py
tests/test_bill_classify.py
tests/test_bill_similarity_search.py
tests/test_segment.py
bpa-0.2.0.dist-info/LICENSE
bpa-0.2.0.dist-info/METADATA
bpa-0.2.0.dist-info/WHEEL
bpa-0.2.0.dist-info/top_level.txt
bpa-0.2.0.dist-info/RECORD
